{"data":{"info":{"site_name":"Lancefestivalen","base_url":"http:\/\/www.lancefestivalen.se"},"files_managed":9,"nodes":94,"users":2,"terms":267,"viewsdata":[],"modules":[{"name":"block","version":"7009","type":"Core","files":[],"lines":0},{"name":"aggregator","version":"7004","type":"Core","files":[],"lines":0},{"name":"biblio_citeproc","version":"7004","type":"Contrib","files":{"sites\/all\/modules\/biblio\/modules\/CiteProc\/biblio_citeproc.install":344,"sites\/all\/modules\/biblio\/modules\/CiteProc\/biblio_citeproc.module":192,"sites\/all\/modules\/biblio\/modules\/CiteProc\/CSL.inc":1745,"sites\/all\/modules\/biblio\/modules\/CiteProc\/locale\/locales-mn-MN.xml":307,"sites\/all\/modules\/biblio\/modules\/CiteProc\/locale\/locales-de-AT.xml":305,"sites\/all\/modules\/biblio\/modules\/CiteProc\/locale\/locales-uk-UA.xml":307,"sites\/all\/modules\/biblio\/modules\/CiteProc\/locale\/locales-fi-FI.xml":305,"sites\/all\/modules\/biblio\/modules\/CiteProc\/locale\/locales-da-DK.xml":306,"sites\/all\/modules\/biblio\/modules\/CiteProc\/locale\/locales-pl-PL.xml":306,"sites\/all\/modules\/biblio\/modules\/CiteProc\/locale\/locales-zh-CN.xml":305,"sites\/all\/modules\/biblio\/modules\/CiteProc\/locale\/locales-zh-TW.xml":306,"sites\/all\/modules\/biblio\/modules\/CiteProc\/locale\/locales-sl-SI.xml":306,"sites\/all\/modules\/biblio\/modules\/CiteProc\/locale\/locales-ru-RU.xml":307,"sites\/all\/modules\/biblio\/modules\/CiteProc\/locale\/locales-pt-PT.xml":306,"sites\/all\/modules\/biblio\/modules\/CiteProc\/locale\/locales-el-GR.xml":306,"sites\/all\/modules\/biblio\/modules\/CiteProc\/locale\/locales-he-IL.xml":305,"sites\/all\/modules\/biblio\/modules\/CiteProc\/locale\/locales-nn-NO.xml":305,"sites\/all\/modules\/biblio\/modules\/CiteProc\/locale\/locales-nl-NL.xml":305,"sites\/all\/modules\/biblio\/modules\/CiteProc\/locale\/locales-pt-BR.xml":305,"sites\/all\/modules\/biblio\/modules\/CiteProc\/locale\/locales-ko-KR.xml":306,"sites\/all\/modules\/biblio\/modules\/CiteProc\/locale\/locales-th-TH.xml":305,"sites\/all\/modules\/biblio\/modules\/CiteProc\/locale\/locales-es-ES.xml":306,"sites\/all\/modules\/biblio\/modules\/CiteProc\/locale\/locales-de-DE.xml":305,"sites\/all\/modules\/biblio\/modules\/CiteProc\/locale\/locales-sk-SK.xml":305,"sites\/all\/modules\/biblio\/modules\/CiteProc\/locale\/locales-af-ZA.xml":306,"sites\/all\/modules\/biblio\/modules\/CiteProc\/locale\/locales-ro-RO.xml":306,"sites\/all\/modules\/biblio\/modules\/CiteProc\/locale\/locales-en-GB.xml":305,"sites\/all\/modules\/biblio\/modules\/CiteProc\/locale\/locales-de-CH.xml":305,"sites\/all\/modules\/biblio\/modules\/CiteProc\/locale\/locales-ar-AR.xml":307,"sites\/all\/modules\/biblio\/modules\/CiteProc\/locale\/locales-nb-NO.xml":305,"sites\/all\/modules\/biblio\/modules\/CiteProc\/locale\/locales-tr-TR.xml":306,"sites\/all\/modules\/biblio\/modules\/CiteProc\/locale\/locales-et-EE.xml":305,"sites\/all\/modules\/biblio\/modules\/CiteProc\/locale\/locales-it-IT.xml":306,"sites\/all\/modules\/biblio\/modules\/CiteProc\/locale\/locales-ja-JP.xml":306,"sites\/all\/modules\/biblio\/modules\/CiteProc\/locale\/locales-bg-BG.xml":306,"sites\/all\/modules\/biblio\/modules\/CiteProc\/locale\/locales-en-US.xml":305,"sites\/all\/modules\/biblio\/modules\/CiteProc\/locale\/locales-is-IS.xml":305,"sites\/all\/modules\/biblio\/modules\/CiteProc\/locale\/locales-ca-AD.xml":306,"sites\/all\/modules\/biblio\/modules\/CiteProc\/locale\/locales-sv-SE.xml":306,"sites\/all\/modules\/biblio\/modules\/CiteProc\/locale\/locales-fr-FR.xml":307,"sites\/all\/modules\/biblio\/modules\/CiteProc\/locale\/locales-eu.xml":305,"sites\/all\/modules\/biblio\/modules\/CiteProc\/locale\/locales-cs-CZ.xml":305,"sites\/all\/modules\/biblio\/modules\/CiteProc\/locale\/locales-hu-HU.xml":306,"sites\/all\/modules\/biblio\/modules\/CiteProc\/locale\/locales-km-KH.xml":305,"sites\/all\/modules\/biblio\/modules\/CiteProc\/locale\/locales-vi-VN.xml":306,"sites\/all\/modules\/biblio\/modules\/CiteProc\/locale\/locales-sr-RS.xml":306,"sites\/all\/modules\/biblio\/modules\/CiteProc\/locale\/locales-fa-IR.xml":304,"sites\/all\/modules\/biblio\/modules\/CiteProc\/style\/nature.csl":115,"sites\/all\/modules\/biblio\/modules\/CiteProc\/style\/apa.csl":444,"sites\/all\/modules\/biblio\/modules\/CiteProc\/style\/cse.csl":185,"sites\/all\/modules\/biblio\/modules\/CiteProc\/style\/harvard1.csl":186,"sites\/all\/modules\/biblio\/modules\/CiteProc\/style\/national-library-of-medicine-grant.csl":255,"sites\/all\/modules\/biblio\/modules\/CiteProc\/style\/apsa.csl":236,"sites\/all\/modules\/biblio\/modules\/CiteProc\/style\/ieee.csl":300,"sites\/all\/modules\/biblio\/modules\/CiteProc\/style\/mhra.csl":417,"sites\/all\/modules\/biblio\/modules\/CiteProc\/style\/chicago-author-date.csl":482,"sites\/all\/modules\/biblio\/modules\/CiteProc\/style\/chicago-note-bibliography.csl":1017,"sites\/all\/modules\/biblio\/modules\/CiteProc\/style\/american-medical-association.csl":238,"sites\/all\/modules\/biblio\/modules\/CiteProc\/style\/chicago-fullnote-bibliography.csl":1046,"sites\/all\/modules\/biblio\/modules\/CiteProc\/style\/asa.csl":227,"sites\/all\/modules\/biblio\/modules\/CiteProc\/style\/vancouver.csl":268,"sites\/all\/modules\/biblio\/modules\/CiteProc\/style\/mla.csl":397,"sites\/all\/modules\/biblio\/modules\/CiteProc\/schema\/csl-terms.rng":149,"sites\/all\/modules\/biblio\/modules\/CiteProc\/schema\/csl.rng":1752,"sites\/all\/modules\/biblio\/modules\/CiteProc\/schema\/csl-variables.rng":103,"sites\/all\/modules\/biblio\/modules\/CiteProc\/schema\/csl-categories.rng":52,"sites\/all\/modules\/biblio\/modules\/CiteProc\/schema\/csl-types.rng":45,"sites\/all\/modules\/biblio\/modules\/CiteProc\/biblio_citeproc.admin.inc":711},"lines":24354},{"name":"blog","version":"0","type":"Core","files":[],"lines":0},{"name":"book","version":"6000","type":"Core","files":[],"lines":0},{"name":"color","version":"7001","type":"Core","files":[],"lines":0},{"name":"comment","version":"7009","type":"Core","files":[],"lines":0},{"name":"contact","version":"7003","type":"Core","files":[],"lines":0},{"name":"contextual","version":"0","type":"Core","files":[],"lines":0},{"name":"ctools","version":"7001","type":"Contrib","files":{"sites\/all\/modules\/ctools\/ctools.api.php":272,"sites\/all\/modules\/ctools\/tests\/ctools_plugin_test.module":73,"sites\/all\/modules\/ctools\/tests\/ctools.plugins.test":101,"sites\/all\/modules\/ctools\/tests\/context.test":87,"sites\/all\/modules\/ctools\/tests\/css.test":82,"sites\/all\/modules\/ctools\/tests\/math_expression_stack.test":64,"sites\/all\/modules\/ctools\/tests\/css_cache.test":49,"sites\/all\/modules\/ctools\/tests\/ctools.drush.sh":120,"sites\/all\/modules\/ctools\/tests\/ctools_export_test\/ctools_export.test":216,"sites\/all\/modules\/ctools\/tests\/ctools_export_test\/ctools_export_test.default_ctools_export_tests.inc":32,"sites\/all\/modules\/ctools\/tests\/ctools_export_test\/ctools_export_test.install":87,"sites\/all\/modules\/ctools\/tests\/ctools_export_test\/ctools_export_test.module":11,"sites\/all\/modules\/ctools\/tests\/plugins\/not_cached\/ctoolsNotCachedPluginArray2.class.php":8,"sites\/all\/modules\/ctools\/tests\/plugins\/not_cached\/plugin_array.inc":21,"sites\/all\/modules\/ctools\/tests\/plugins\/not_cached\/ctoolsNotCachedPluginArray.class.php":8,"sites\/all\/modules\/ctools\/tests\/plugins\/not_cached\/plugin_array_dne.inc":16,"sites\/all\/modules\/ctools\/tests\/plugins\/not_cached\/plugin_array2.inc":21,"sites\/all\/modules\/ctools\/tests\/plugins\/cached\/plugin_array.inc":21,"sites\/all\/modules\/ctools\/tests\/plugins\/cached\/ctoolsCachedPluginArray2.class.php":8,"sites\/all\/modules\/ctools\/tests\/plugins\/cached\/ctoolsCachedPluginArray.class.php":8,"sites\/all\/modules\/ctools\/tests\/plugins\/cached\/plugin_array_dne.inc":16,"sites\/all\/modules\/ctools\/tests\/plugins\/cached\/plugin_array2.inc":21,"sites\/all\/modules\/ctools\/tests\/math_expression.test":130,"sites\/all\/modules\/ctools\/tests\/object_cache.test":47,"sites\/all\/modules\/ctools\/drush\/ctools.drush.inc":1018,"sites\/all\/modules\/ctools\/ctools_plugin_example\/ctools_plugin_example.module":95,"sites\/all\/modules\/ctools\/ctools_plugin_example\/ctools_plugin_example.pages_default.inc":451,"sites\/all\/modules\/ctools\/ctools_plugin_example\/plugins\/contexts\/relcontext.inc":84,"sites\/all\/modules\/ctools\/ctools_plugin_example\/plugins\/contexts\/simplecontext.inc":135,"sites\/all\/modules\/ctools\/ctools_plugin_example\/plugins\/access\/arg_length.inc":66,"sites\/all\/modules\/ctools\/ctools_plugin_example\/plugins\/access\/example_role.inc":77,"sites\/all\/modules\/ctools\/ctools_plugin_example\/plugins\/content_types\/no_context_content_type.inc":117,"sites\/all\/modules\/ctools\/ctools_plugin_example\/plugins\/content_types\/relcontext_content_type.inc":104,"sites\/all\/modules\/ctools\/ctools_plugin_example\/plugins\/content_types\/simplecontext_content_type.inc":130,"sites\/all\/modules\/ctools\/ctools_plugin_example\/plugins\/arguments\/simplecontext_arg.inc":53,"sites\/all\/modules\/ctools\/ctools_plugin_example\/plugins\/panels.pages.inc":215,"sites\/all\/modules\/ctools\/ctools_plugin_example\/plugins\/relationships\/relcontext_from_simplecontext.inc":51,"sites\/all\/modules\/ctools\/ctools_plugin_example\/help\/Context-plugins--Creating-a--context--from-an-argument.html":22,"sites\/all\/modules\/ctools\/ctools_plugin_example\/help\/Argument-Plugins--Starting-at-the-beginning.html":21,"sites\/all\/modules\/ctools\/ctools_plugin_example\/help\/Content-Type-Plugins--Displaying-content-using-a-context.html":18,"sites\/all\/modules\/ctools\/ctools_plugin_example\/help\/Relationships--Letting-one-context-take-us-to-another.html":19,"sites\/all\/modules\/ctools\/ctools_plugin_example\/help\/Module-setup-and-hooks.html":21,"sites\/all\/modules\/ctools\/ctools_plugin_example\/help\/Chaos-Tools--CTools--Plugin-Examples.html":20,"sites\/all\/modules\/ctools\/ctools_plugin_example\/help\/Access-Plugins--Determining-access-and-visibility.html":18,"sites\/all\/modules\/ctools\/ctools_plugin_example\/help\/ctools_plugin_example.help.ini":43,"sites\/all\/modules\/ctools\/views_content\/views_content.admin.inc":1,"sites\/all\/modules\/ctools\/views_content\/plugins\/contexts\/view.inc":175,"sites\/all\/modules\/ctools\/views_content\/plugins\/views\/views_content_plugin_style_ctools_context.inc":54,"sites\/all\/modules\/ctools\/views_content\/plugins\/views\/views_content_plugin_display_ctools_context.inc":273,"sites\/all\/modules\/ctools\/views_content\/plugins\/views\/views_content.views.inc":66,"sites\/all\/modules\/ctools\/views_content\/plugins\/views\/views_content_plugin_display_panel_pane.inc":569,"sites\/all\/modules\/ctools\/views_content\/plugins\/content_types\/views.inc":557,"sites\/all\/modules\/ctools\/views_content\/plugins\/content_types\/views_empty.inc":54,"sites\/all\/modules\/ctools\/views_content\/plugins\/content_types\/views_attachments.inc":76,"sites\/all\/modules\/ctools\/views_content\/plugins\/content_types\/views_panes.inc":521,"sites\/all\/modules\/ctools\/views_content\/plugins\/content_types\/views_view.inc":53,"sites\/all\/modules\/ctools\/views_content\/plugins\/content_types\/views_footer.inc":52,"sites\/all\/modules\/ctools\/views_content\/plugins\/content_types\/views_row.inc":238,"sites\/all\/modules\/ctools\/views_content\/plugins\/content_types\/views_pager.inc":53,"sites\/all\/modules\/ctools\/views_content\/plugins\/content_types\/views_header.inc":52,"sites\/all\/modules\/ctools\/views_content\/plugins\/content_types\/views_feed.inc":52,"sites\/all\/modules\/ctools\/views_content\/plugins\/content_types\/views_exposed.inc":52,"sites\/all\/modules\/ctools\/views_content\/plugins\/relationships\/term_from_view.inc":65,"sites\/all\/modules\/ctools\/views_content\/plugins\/relationships\/view_from_argument.inc":101,"sites\/all\/modules\/ctools\/views_content\/plugins\/relationships\/user_from_view.inc":65,"sites\/all\/modules\/ctools\/views_content\/plugins\/relationships\/node_from_view.inc":65,"sites\/all\/modules\/ctools\/views_content\/views_content.module":319,"sites\/all\/modules\/ctools\/ctools.module":1095,"sites\/all\/modules\/ctools\/ctools_custom_content\/ctools_custom_content.install":68,"sites\/all\/modules\/ctools\/ctools_custom_content\/plugins\/export_ui\/ctools_custom_content_ui.class.php":147,"sites\/all\/modules\/ctools\/ctools_custom_content\/plugins\/export_ui\/ctools_custom_content.inc":21,"sites\/all\/modules\/ctools\/ctools_custom_content\/ctools_custom_content.module":119,"sites\/all\/modules\/ctools\/plugins\/contexts\/node_edit_form.inc":193,"sites\/all\/modules\/ctools\/plugins\/contexts\/string.inc":91,"sites\/all\/modules\/ctools\/plugins\/contexts\/terms.inc":99,"sites\/all\/modules\/ctools\/plugins\/contexts\/term.inc":167,"sites\/all\/modules\/ctools\/plugins\/contexts\/user_edit_form.inc":193,"sites\/all\/modules\/ctools\/plugins\/contexts\/node_add_form.inc":125,"sites\/all\/modules\/ctools\/plugins\/contexts\/entity.inc":274,"sites\/all\/modules\/ctools\/plugins\/contexts\/vocabulary.inc":73,"sites\/all\/modules\/ctools\/plugins\/contexts\/token.inc":63,"sites\/all\/modules\/ctools\/plugins\/contexts\/node.inc":182,"sites\/all\/modules\/ctools\/plugins\/contexts\/query_string.inc":90,"sites\/all\/modules\/ctools\/plugins\/contexts\/user.inc":177,"sites\/all\/modules\/ctools\/plugins\/cache\/simple.inc":52,"sites\/all\/modules\/ctools\/plugins\/cache\/export_ui.inc":40,"sites\/all\/modules\/ctools\/plugins\/access\/book.inc":95,"sites\/all\/modules\/ctools\/plugins\/access\/site_language.inc":88,"sites\/all\/modules\/ctools\/plugins\/access\/path_visibility.inc":89,"sites\/all\/modules\/ctools\/plugins\/access\/node_language.inc":115,"sites\/all\/modules\/ctools\/plugins\/access\/string_equal.inc":95,"sites\/all\/modules\/ctools\/plugins\/access\/term_has_parent.inc":173,"sites\/all\/modules\/ctools\/plugins\/access\/context_exists.inc":52,"sites\/all\/modules\/ctools\/plugins\/access\/term.inc":130,"sites\/all\/modules\/ctools\/plugins\/access\/node_access.inc":90,"sites\/all\/modules\/ctools\/plugins\/access\/front.inc":47,"sites\/all\/modules\/ctools\/plugins\/access\/role.inc":80,"sites\/all\/modules\/ctools\/plugins\/access\/entity_bundle.inc":137,"sites\/all\/modules\/ctools\/plugins\/access\/term_vocabulary.inc":128,"sites\/all\/modules\/ctools\/plugins\/access\/node_comment.inc":32,"sites\/all\/modules\/ctools\/plugins\/access\/node_status.inc":34,"sites\/all\/modules\/ctools\/plugins\/access\/node_type.inc":118,"sites\/all\/modules\/ctools\/plugins\/access\/theme.inc":71,"sites\/all\/modules\/ctools\/plugins\/access\/perm.inc":74,"sites\/all\/modules\/ctools\/plugins\/access\/term_parent.inc":87,"sites\/all\/modules\/ctools\/plugins\/access\/query_string_exists.inc":45,"sites\/all\/modules\/ctools\/plugins\/access\/node.inc":1,"sites\/all\/modules\/ctools\/plugins\/access\/string_length.inc":81,"sites\/all\/modules\/ctools\/plugins\/access\/entity_field_value.inc":411,"sites\/all\/modules\/ctools\/plugins\/access\/php.inc":65,"sites\/all\/modules\/ctools\/plugins\/access\/compare_users.inc":71,"sites\/all\/modules\/ctools\/plugins\/export_ui\/ctools_export_ui.inc":25,"sites\/all\/modules\/ctools\/plugins\/export_ui\/ctools_export_ui.class.php":1538,"sites\/all\/modules\/ctools\/plugins\/content_types\/node_form\/node_form_publishing.inc":55,"sites\/all\/modules\/ctools\/plugins\/content_types\/node_form\/node_form_comment.inc":51,"sites\/all\/modules\/ctools\/plugins\/content_types\/node_form\/node_form_author.inc":53,"sites\/all\/modules\/ctools\/plugins\/content_types\/node_form\/node_form_attachments.inc":52,"sites\/all\/modules\/ctools\/plugins\/content_types\/node_form\/node_form_buttons.inc":44,"sites\/all\/modules\/ctools\/plugins\/content_types\/node_form\/node_form_title.inc":42,"sites\/all\/modules\/ctools\/plugins\/content_types\/node_form\/node_form_log.inc":48,"sites\/all\/modules\/ctools\/plugins\/content_types\/node_form\/node_form_path.inc":52,"sites\/all\/modules\/ctools\/plugins\/content_types\/node_form\/node_form_menu.inc":51,"sites\/all\/modules\/ctools\/plugins\/content_types\/node_form\/node_form_book.inc":51,"sites\/all\/modules\/ctools\/plugins\/content_types\/node_form\/node_form_language.inc":41,"sites\/all\/modules\/ctools\/plugins\/content_types\/entity_context\/entity_field.inc":278,"sites\/all\/modules\/ctools\/plugins\/content_types\/entity_context\/entity_field_extra.inc":134,"sites\/all\/modules\/ctools\/plugins\/content_types\/node_context\/node_type_desc.inc":48,"sites\/all\/modules\/ctools\/plugins\/content_types\/node_context\/node_attachments.inc":45,"sites\/all\/modules\/ctools\/plugins\/content_types\/node_context\/node_links.inc":106,"sites\/all\/modules\/ctools\/plugins\/content_types\/node_context\/node_body.inc":41,"sites\/all\/modules\/ctools\/plugins\/content_types\/node_context\/node_book_children.inc":44,"sites\/all\/modules\/ctools\/plugins\/content_types\/node_context\/node_book_nav.inc":44,"sites\/all\/modules\/ctools\/plugins\/content_types\/node_context\/node_book_menu.inc":102,"sites\/all\/modules\/ctools\/plugins\/content_types\/node_context\/node_comments.inc":99,"sites\/all\/modules\/ctools\/plugins\/content_types\/node_context\/node_title.inc":121,"sites\/all\/modules\/ctools\/plugins\/content_types\/node_context\/node_author.inc":72,"sites\/all\/modules\/ctools\/plugins\/content_types\/node_context\/node_comment_form.inc":80,"sites\/all\/modules\/ctools\/plugins\/content_types\/node_context\/node_updated.inc":76,"sites\/all\/modules\/ctools\/plugins\/content_types\/node_context\/node_comment_wrapper.inc":118,"sites\/all\/modules\/ctools\/plugins\/content_types\/node_context\/node_terms.inc":206,"sites\/all\/modules\/ctools\/plugins\/content_types\/node_context\/node_content.inc":205,"sites\/all\/modules\/ctools\/plugins\/content_types\/node_context\/node_created.inc":75,"sites\/all\/modules\/ctools\/plugins\/content_types\/contact\/contact.inc":61,"sites\/all\/modules\/ctools\/plugins\/content_types\/contact\/user_contact.inc":67,"sites\/all\/modules\/ctools\/plugins\/content_types\/custom\/custom.inc":464,"sites\/all\/modules\/ctools\/plugins\/content_types\/term_context\/term_description.inc":52,"sites\/all\/modules\/ctools\/plugins\/content_types\/term_context\/term_name.inc":122,"sites\/all\/modules\/ctools\/plugins\/content_types\/term_context\/term_list.inc":173,"sites\/all\/modules\/ctools\/plugins\/content_types\/user_context\/user_signature.inc":44,"sites\/all\/modules\/ctools\/plugins\/content_types\/user_context\/user_links.inc":85,"sites\/all\/modules\/ctools\/plugins\/content_types\/user_context\/profile_fields.inc":130,"sites\/all\/modules\/ctools\/plugins\/content_types\/user_context\/profile_fields_pane.tpl.php":17,"sites\/all\/modules\/ctools\/plugins\/content_types\/user_context\/user_picture.inc":55,"sites\/all\/modules\/ctools\/plugins\/content_types\/user_context\/user_profile.inc":88,"sites\/all\/modules\/ctools\/plugins\/content_types\/vocabulary_context\/vocabulary_terms.inc":101,"sites\/all\/modules\/ctools\/plugins\/content_types\/form\/form.inc":63,"sites\/all\/modules\/ctools\/plugins\/content_types\/form\/entity_form_field.inc":168,"sites\/all\/modules\/ctools\/plugins\/content_types\/node\/node.inc":252,"sites\/all\/modules\/ctools\/plugins\/content_types\/block\/block.inc":566,"sites\/all\/modules\/ctools\/plugins\/content_types\/token\/token.inc":123,"sites\/all\/modules\/ctools\/plugins\/content_types\/search\/search_form.inc":157,"sites\/all\/modules\/ctools\/plugins\/content_types\/search\/search_result.inc":205,"sites\/all\/modules\/ctools\/plugins\/content_types\/comment\/comment_created.inc":75,"sites\/all\/modules\/ctools\/plugins\/content_types\/comment\/comment_links.inc":81,"sites\/all\/modules\/ctools\/plugins\/content_types\/comment\/comment_reply_form.inc":51,"sites\/all\/modules\/ctools\/plugins\/content_types\/page\/page_title.inc":122,"sites\/all\/modules\/ctools\/plugins\/content_types\/page\/page_actions.inc":33,"sites\/all\/modules\/ctools\/plugins\/content_types\/page\/page_secondary_links.inc":41,"sites\/all\/modules\/ctools\/plugins\/content_types\/page\/page_primary_links.inc":41,"sites\/all\/modules\/ctools\/plugins\/content_types\/page\/page_help.inc":34,"sites\/all\/modules\/ctools\/plugins\/content_types\/page\/page_slogan.inc":33,"sites\/all\/modules\/ctools\/plugins\/content_types\/page\/page_logo.inc":38,"sites\/all\/modules\/ctools\/plugins\/content_types\/page\/page_tabs.inc":90,"sites\/all\/modules\/ctools\/plugins\/content_types\/page\/page_site_name.inc":69,"sites\/all\/modules\/ctools\/plugins\/content_types\/page\/page_feed_icons.inc":33,"sites\/all\/modules\/ctools\/plugins\/content_types\/page\/page_messages.inc":34,"sites\/all\/modules\/ctools\/plugins\/content_types\/page\/page_breadcrumb.inc":33,"sites\/all\/modules\/ctools\/plugins\/arguments\/string.inc":64,"sites\/all\/modules\/ctools\/plugins\/arguments\/terms.inc":79,"sites\/all\/modules\/ctools\/plugins\/arguments\/vid.inc":47,"sites\/all\/modules\/ctools\/plugins\/arguments\/uid.inc":54,"sites\/all\/modules\/ctools\/plugins\/arguments\/term.inc":204,"sites\/all\/modules\/ctools\/plugins\/arguments\/node_edit.inc":52,"sites\/all\/modules\/ctools\/plugins\/arguments\/rid.inc":51,"sites\/all\/modules\/ctools\/plugins\/arguments\/user_edit.inc":47,"sites\/all\/modules\/ctools\/plugins\/arguments\/nid.inc":51,"sites\/all\/modules\/ctools\/plugins\/arguments\/node_add.inc":33,"sites\/all\/modules\/ctools\/plugins\/arguments\/user_name.inc":48,"sites\/all\/modules\/ctools\/plugins\/arguments\/entity_id.inc":148,"sites\/all\/modules\/ctools\/plugins\/relationships\/book_parent.inc":69,"sites\/all\/modules\/ctools\/plugins\/relationships\/entity_from_query_string.inc":71,"sites\/all\/modules\/ctools\/plugins\/relationships\/terms_from_node.inc":84,"sites\/all\/modules\/ctools\/plugins\/relationships\/entity_from_field.inc":230,"sites\/all\/modules\/ctools\/plugins\/relationships\/node_edit_form_from_node.inc":32,"sites\/all\/modules\/ctools\/plugins\/relationships\/user_from_node.inc":39,"sites\/all\/modules\/ctools\/plugins\/relationships\/term_parent.inc":69,"sites\/all\/modules\/ctools\/plugins\/relationships\/entity_from_schema.inc":137,"sites\/all\/modules\/ctools\/plugins\/relationships\/user_category_edit_form_from_user.inc":62,"sites\/all\/modules\/ctools\/plugins\/relationships\/term_from_node.inc":61,"sites\/all\/modules\/ctools\/help\/ajax.html":1,"sites\/all\/modules\/ctools\/help\/context-access.html":12,"sites\/all\/modules\/ctools\/help\/modal.html":216,"sites\/all\/modules\/ctools\/help\/form.html":2,"sites\/all\/modules\/ctools\/help\/plugins.html":6,"sites\/all\/modules\/ctools\/help\/plugins-implementing.html":63,"sites\/all\/modules\/ctools\/help\/plugins-creating.html":204,"sites\/all\/modules\/ctools\/help\/context-arguments.html":15,"sites\/all\/modules\/ctools\/help\/object-cache.html":133,"sites\/all\/modules\/ctools\/help\/ctools.help.ini":98,"sites\/all\/modules\/ctools\/help\/dropbutton.html":2,"sites\/all\/modules\/ctools\/help\/context.html":1,"sites\/all\/modules\/ctools\/help\/context-content.html":158,"sites\/all\/modules\/ctools\/help\/collapsible-div.html":2,"sites\/all\/modules\/ctools\/help\/context-context.html":13,"sites\/all\/modules\/ctools\/help\/context-relationships.html":14,"sites\/all\/modules\/ctools\/help\/about.html":30,"sites\/all\/modules\/ctools\/help\/export.html":295,"sites\/all\/modules\/ctools\/help\/wizard.html":312,"sites\/all\/modules\/ctools\/help\/export-ui.html":86,"sites\/all\/modules\/ctools\/help\/css.html":2,"sites\/all\/modules\/ctools\/help\/dependent.html":2,"sites\/all\/modules\/ctools\/help\/dropdown.html":2,"sites\/all\/modules\/ctools\/help\/plugins-api.html":56,"sites\/all\/modules\/ctools\/ctools_ajax_sample\/ctools_ajax_sample.install":20,"sites\/all\/modules\/ctools\/ctools_ajax_sample\/ctools_ajax_sample.module":757,"sites\/all\/modules\/ctools\/ctools_ajax_sample\/css\/ctools-ajax-sample.css":135,"sites\/all\/modules\/ctools\/ctools_ajax_sample\/js\/ctools-ajax-sample.js":43,"sites\/all\/modules\/ctools\/term_depth\/term_depth.module":8,"sites\/all\/modules\/ctools\/term_depth\/plugins\/access\/term_depth.inc":139,"sites\/all\/modules\/ctools\/css\/ruleset.css":12,"sites\/all\/modules\/ctools\/css\/collapsible-div.css":27,"sites\/all\/modules\/ctools\/css\/button.css":33,"sites\/all\/modules\/ctools\/css\/stylizer.css":130,"sites\/all\/modules\/ctools\/css\/ctools.css":26,"sites\/all\/modules\/ctools\/css\/wizard.css":9,"sites\/all\/modules\/ctools\/css\/modal.css":131,"sites\/all\/modules\/ctools\/css\/dropbutton.css":67,"sites\/all\/modules\/ctools\/css\/dropdown.css":74,"sites\/all\/modules\/ctools\/css\/modal-rtl.css":61,"sites\/all\/modules\/ctools\/css\/context.css":11,"sites\/all\/modules\/ctools\/css\/export-ui-list.css":46,"sites\/all\/modules\/ctools\/includes\/views.inc":27,"sites\/all\/modules\/ctools\/includes\/css-cache.inc":53,"sites\/all\/modules\/ctools\/includes\/action-links.theme.inc":33,"sites\/all\/modules\/ctools\/includes\/menu.inc":99,"sites\/all\/modules\/ctools\/includes\/cache.plugin-type.inc":12,"sites\/all\/modules\/ctools\/includes\/css.inc":576,"sites\/all\/modules\/ctools\/includes\/dropbutton.theme.inc":144,"sites\/all\/modules\/ctools\/includes\/context-access-admin.inc":486,"sites\/all\/modules\/ctools\/includes\/context-admin.inc":850,"sites\/all\/modules\/ctools\/includes\/stylizer.inc":1655,"sites\/all\/modules\/ctools\/includes\/export-ui.inc":476,"sites\/all\/modules\/ctools\/includes\/content.theme.inc":22,"sites\/all\/modules\/ctools\/includes\/export-ui.menu.inc":25,"sites\/all\/modules\/ctools\/includes\/ajax.inc":158,"sites\/all\/modules\/ctools\/includes\/wizard.inc":535,"sites\/all\/modules\/ctools\/includes\/page-wizard.inc":195,"sites\/all\/modules\/ctools\/includes\/dropdown.theme.inc":91,"sites\/all\/modules\/ctools\/includes\/context.theme.inc":345,"sites\/all\/modules\/ctools\/includes\/context.inc":1604,"sites\/all\/modules\/ctools\/includes\/entity-access.inc":151,"sites\/all\/modules\/ctools\/includes\/plugins-admin.inc":209,"sites\/all\/modules\/ctools\/includes\/math-expr.inc":389,"sites\/all\/modules\/ctools\/includes\/context.plugin-type.inc":25,"sites\/all\/modules\/ctools\/includes\/content.plugin-type.inc":17,"sites\/all\/modules\/ctools\/includes\/plugins.inc":922,"sites\/all\/modules\/ctools\/includes\/collapsible.theme.inc":80,"sites\/all\/modules\/ctools\/includes\/export.inc":1269,"sites\/all\/modules\/ctools\/includes\/export-ui.plugin-type.inc":20,"sites\/all\/modules\/ctools\/includes\/page-wizard.menu.inc":33,"sites\/all\/modules\/ctools\/includes\/registry.inc":78,"sites\/all\/modules\/ctools\/includes\/dependent.inc":182,"sites\/all\/modules\/ctools\/includes\/cache.inc":170,"sites\/all\/modules\/ctools\/includes\/stylizer.theme.inc":29,"sites\/all\/modules\/ctools\/includes\/uuid.inc":71,"sites\/all\/modules\/ctools\/includes\/object-cache.inc":206,"sites\/all\/modules\/ctools\/includes\/modal.inc":263,"sites\/all\/modules\/ctools\/includes\/content.inc":860,"sites\/all\/modules\/ctools\/includes\/context.menu.inc":41,"sites\/all\/modules\/ctools\/includes\/context-task-handler.inc":541,"sites\/all\/modules\/ctools\/includes\/jump-menu.inc":151,"sites\/all\/modules\/ctools\/includes\/language.inc":44,"sites\/all\/modules\/ctools\/includes\/fields.inc":357,"sites\/all\/modules\/ctools\/includes\/object-cache.cron.inc":17,"sites\/all\/modules\/ctools\/includes\/cleanstring.inc":205,"sites\/all\/modules\/ctools\/includes\/content.menu.inc":180,"sites\/all\/modules\/ctools\/includes\/wizard.theme.inc":23,"sites\/all\/modules\/ctools\/includes\/utility.inc":32,"sites\/all\/modules\/ctools\/page_manager\/page_manager.admin.inc":1928,"sites\/all\/modules\/ctools\/page_manager\/page_manager.install":205,"sites\/all\/modules\/ctools\/page_manager\/page_manager.module":1350,"sites\/all\/modules\/ctools\/page_manager\/theme\/page_manager.theme.inc":119,"sites\/all\/modules\/ctools\/page_manager\/theme\/page-manager-edit-page.tpl.php":53,"sites\/all\/modules\/ctools\/page_manager\/plugins\/cache\/page_manager_context.inc":71,"sites\/all\/modules\/ctools\/page_manager\/plugins\/tasks\/poll.inc":122,"sites\/all\/modules\/ctools\/page_manager\/plugins\/tasks\/node_edit.inc":186,"sites\/all\/modules\/ctools\/page_manager\/plugins\/tasks\/page.inc":788,"sites\/all\/modules\/ctools\/page_manager\/plugins\/tasks\/user_edit.inc":188,"sites\/all\/modules\/ctools\/page_manager\/plugins\/tasks\/blog_user.inc":153,"sites\/all\/modules\/ctools\/page_manager\/plugins\/tasks\/search.inc":250,"sites\/all\/modules\/ctools\/page_manager\/plugins\/tasks\/blog.inc":122,"sites\/all\/modules\/ctools\/page_manager\/plugins\/tasks\/contact_user.inc":156,"sites\/all\/modules\/ctools\/page_manager\/plugins\/tasks\/page.admin.inc":1531,"sites\/all\/modules\/ctools\/page_manager\/plugins\/tasks\/contact_site.inc":130,"sites\/all\/modules\/ctools\/page_manager\/plugins\/tasks\/term_view.inc":378,"sites\/all\/modules\/ctools\/page_manager\/plugins\/tasks\/comment_reply.inc":163,"sites\/all\/modules\/ctools\/page_manager\/plugins\/tasks\/node_view.inc":167,"sites\/all\/modules\/ctools\/page_manager\/plugins\/tasks\/user_view.inc":162,"sites\/all\/modules\/ctools\/page_manager\/plugins\/task_handlers\/http_response.inc":335,"sites\/all\/modules\/ctools\/page_manager\/page_manager.api.php":40,"sites\/all\/modules\/ctools\/page_manager\/help\/custom-pages-menu.html":2,"sites\/all\/modules\/ctools\/page_manager\/help\/page-task-type.html":4,"sites\/all\/modules\/ctools\/page_manager\/help\/getting-started-create.html":2,"sites\/all\/modules\/ctools\/page_manager\/help\/getting-started.html":16,"sites\/all\/modules\/ctools\/page_manager\/help\/custom-pages-arguments.html":2,"sites\/all\/modules\/ctools\/page_manager\/help\/variants.html":2,"sites\/all\/modules\/ctools\/page_manager\/help\/getting-started-page-list.html":2,"sites\/all\/modules\/ctools\/page_manager\/help\/getting-started-custom-nodes.html":2,"sites\/all\/modules\/ctools\/page_manager\/help\/api-task-handler.html":43,"sites\/all\/modules\/ctools\/page_manager\/help\/custom-pages.html":2,"sites\/all\/modules\/ctools\/page_manager\/help\/api-task-type.html":2,"sites\/all\/modules\/ctools\/page_manager\/help\/getting-started-members.html":2,"sites\/all\/modules\/ctools\/page_manager\/help\/getting-started-custom-vocabulary.html":2,"sites\/all\/modules\/ctools\/page_manager\/help\/about.html":11,"sites\/all\/modules\/ctools\/page_manager\/help\/custom-pages-access.html":2,"sites\/all\/modules\/ctools\/page_manager\/help\/page_manager.help.ini":60,"sites\/all\/modules\/ctools\/page_manager\/help\/api-task.html":39,"sites\/all\/modules\/ctools\/page_manager\/css\/page-manager.css":373,"sites\/all\/modules\/ctools\/page_manager\/js\/page-list.js":45,"sites\/all\/modules\/ctools\/js\/dropbutton.js":95,"sites\/all\/modules\/ctools\/js\/modal.js":700,"sites\/all\/modules\/ctools\/js\/ajax-responder.js":127,"sites\/all\/modules\/ctools\/js\/states-show.js":44,"sites\/all\/modules\/ctools\/js\/stylizer.js":221,"sites\/all\/modules\/ctools\/js\/dropdown.js":88,"sites\/all\/modules\/ctools\/js\/auto-submit.js":103,"sites\/all\/modules\/ctools\/js\/dependent.js":245,"sites\/all\/modules\/ctools\/js\/collapsible-div.js":242,"sites\/all\/modules\/ctools\/js\/jump-menu.js":43,"sites\/all\/modules\/ctools\/stylizer\/stylizer.module":136,"sites\/all\/modules\/ctools\/stylizer\/plugins\/export_ui\/stylizer.inc":46,"sites\/all\/modules\/ctools\/stylizer\/plugins\/export_ui\/stylizer_ui.class.php":273,"sites\/all\/modules\/ctools\/stylizer\/stylizer.install":71,"sites\/all\/modules\/ctools\/ctools_access_ruleset\/ctools_access_ruleset.install":83,"sites\/all\/modules\/ctools\/ctools_access_ruleset\/ctools_access_ruleset.module":86,"sites\/all\/modules\/ctools\/ctools_access_ruleset\/plugins\/access\/ruleset.inc":110,"sites\/all\/modules\/ctools\/ctools_access_ruleset\/plugins\/export_ui\/ctools_access_ruleset.inc":30,"sites\/all\/modules\/ctools\/ctools_access_ruleset\/plugins\/export_ui\/ctools_access_ruleset_ui.class.php":54,"sites\/all\/modules\/ctools\/bulk_export\/bulk_export.js":30,"sites\/all\/modules\/ctools\/bulk_export\/bulk_export.css":19,"sites\/all\/modules\/ctools\/bulk_export\/bulk_export.module":280,"sites\/all\/modules\/ctools\/ctools.install":266},"lines":53025},{"name":"dashboard","version":"0","type":"Core","files":[],"lines":0},{"name":"disqus","version":"7002","type":"Contrib","files":{"sites\/all\/modules\/disqus\/disqus.php":387,"sites\/all\/modules\/disqus\/disqus.module":1109,"sites\/all\/modules\/disqus\/disqus_ds\/disqus_ds.module":89,"sites\/all\/modules\/disqus\/disqus.views.inc":79,"sites\/all\/modules\/disqus\/disqus.admin.inc":242,"sites\/all\/modules\/disqus\/disqus.api.php":34,"sites\/all\/modules\/disqus\/disqus.js":90,"sites\/all\/modules\/disqus\/disqus.install":101,"sites\/all\/modules\/disqus\/disqus-node-form.js":15},"lines":2146},{"name":"entity","version":"7003","type":"Contrib","files":{"sites\/all\/modules\/entity\/entity_token.tokens.inc":344,"sites\/all\/modules\/entity\/entity.module":1575,"sites\/all\/modules\/entity\/entity.i18n.inc":211,"sites\/all\/modules\/entity\/tests\/entity_test.module":288,"sites\/all\/modules\/entity\/tests\/entity_feature.module":33,"sites\/all\/modules\/entity\/tests\/entity_test_i18n.module":54,"sites\/all\/modules\/entity\/tests\/entity_test.install":171,"sites\/all\/modules\/entity\/entity.rules.inc":119,"sites\/all\/modules\/entity\/ctools\/content_types\/entity_view.inc":134,"sites\/all\/modules\/entity\/ctools\/relationships\/entity_property.inc":154,"sites\/all\/modules\/entity\/entity.test":2124,"sites\/all\/modules\/entity\/theme\/entity.theme.css":5,"sites\/all\/modules\/entity\/theme\/entity.theme.inc":216,"sites\/all\/modules\/entity\/theme\/entity.tpl.php":49,"sites\/all\/modules\/entity\/modules\/callbacks.inc":1100,"sites\/all\/modules\/entity\/views\/entity.views.inc":724,"sites\/all\/modules\/entity\/views\/handlers\/entity_views_handler_field_text.inc":102,"sites\/all\/modules\/entity\/views\/handlers\/entity_views_field_handler_helper.inc":528,"sites\/all\/modules\/entity\/views\/handlers\/entity_views_handler_field_options.inc":121,"sites\/all\/modules\/entity\/views\/handlers\/entity_views_handler_relationship_by_bundle.inc":118,"sites\/all\/modules\/entity\/views\/handlers\/entity_views_handler_field_duration.inc":133,"sites\/all\/modules\/entity\/views\/handlers\/entity_views_handler_field_field.inc":106,"sites\/all\/modules\/entity\/views\/handlers\/entity_views_handler_field_boolean.inc":100,"sites\/all\/modules\/entity\/views\/handlers\/entity_views_handler_field_uri.inc":100,"sites\/all\/modules\/entity\/views\/handlers\/entity_views_handler_field_numeric.inc":100,"sites\/all\/modules\/entity\/views\/handlers\/entity_views_handler_area_entity.inc":121,"sites\/all\/modules\/entity\/views\/handlers\/entity_views_handler_field_entity.inc":208,"sites\/all\/modules\/entity\/views\/handlers\/entity_views_handler_relationship.inc":52,"sites\/all\/modules\/entity\/views\/handlers\/entity_views_handler_field_date.inc":100,"sites\/all\/modules\/entity\/views\/plugins\/entity_views_plugin_row_entity_view.inc":99,"sites\/all\/modules\/entity\/views\/entity_views_example_query.php":89,"sites\/all\/modules\/entity\/entity.install":143,"sites\/all\/modules\/entity\/entity.api.php":468,"sites\/all\/modules\/entity\/entity_token.module":7,"sites\/all\/modules\/entity\/entity.features.inc":205,"sites\/all\/modules\/entity\/includes\/entity.inc":424,"sites\/all\/modules\/entity\/includes\/entity.controller.inc":982,"sites\/all\/modules\/entity\/includes\/entity.wrapper.inc":1274,"sites\/all\/modules\/entity\/includes\/entity.property.inc":658,"sites\/all\/modules\/entity\/includes\/entity.ui.inc":768},"lines":14307},{"name":"entity_token","version":"0","type":"Contrib","files":{"sites\/all\/modules\/entity\/entity_token.tokens.inc":344,"sites\/all\/modules\/entity\/entity.module":1575,"sites\/all\/modules\/entity\/entity.i18n.inc":211,"sites\/all\/modules\/entity\/tests\/entity_test.module":288,"sites\/all\/modules\/entity\/tests\/entity_feature.module":33,"sites\/all\/modules\/entity\/tests\/entity_test_i18n.module":54,"sites\/all\/modules\/entity\/tests\/entity_test.install":171,"sites\/all\/modules\/entity\/entity.rules.inc":119,"sites\/all\/modules\/entity\/ctools\/content_types\/entity_view.inc":134,"sites\/all\/modules\/entity\/ctools\/relationships\/entity_property.inc":154,"sites\/all\/modules\/entity\/entity.test":2124,"sites\/all\/modules\/entity\/theme\/entity.theme.css":5,"sites\/all\/modules\/entity\/theme\/entity.theme.inc":216,"sites\/all\/modules\/entity\/theme\/entity.tpl.php":49,"sites\/all\/modules\/entity\/modules\/callbacks.inc":1100,"sites\/all\/modules\/entity\/views\/entity.views.inc":724,"sites\/all\/modules\/entity\/views\/handlers\/entity_views_handler_field_text.inc":102,"sites\/all\/modules\/entity\/views\/handlers\/entity_views_field_handler_helper.inc":528,"sites\/all\/modules\/entity\/views\/handlers\/entity_views_handler_field_options.inc":121,"sites\/all\/modules\/entity\/views\/handlers\/entity_views_handler_relationship_by_bundle.inc":118,"sites\/all\/modules\/entity\/views\/handlers\/entity_views_handler_field_duration.inc":133,"sites\/all\/modules\/entity\/views\/handlers\/entity_views_handler_field_field.inc":106,"sites\/all\/modules\/entity\/views\/handlers\/entity_views_handler_field_boolean.inc":100,"sites\/all\/modules\/entity\/views\/handlers\/entity_views_handler_field_uri.inc":100,"sites\/all\/modules\/entity\/views\/handlers\/entity_views_handler_field_numeric.inc":100,"sites\/all\/modules\/entity\/views\/handlers\/entity_views_handler_area_entity.inc":121,"sites\/all\/modules\/entity\/views\/handlers\/entity_views_handler_field_entity.inc":208,"sites\/all\/modules\/entity\/views\/handlers\/entity_views_handler_relationship.inc":52,"sites\/all\/modules\/entity\/views\/handlers\/entity_views_handler_field_date.inc":100,"sites\/all\/modules\/entity\/views\/plugins\/entity_views_plugin_row_entity_view.inc":99,"sites\/all\/modules\/entity\/views\/entity_views_example_query.php":89,"sites\/all\/modules\/entity\/entity.install":143,"sites\/all\/modules\/entity\/entity.api.php":468,"sites\/all\/modules\/entity\/entity_token.module":7,"sites\/all\/modules\/entity\/entity.features.inc":205,"sites\/all\/modules\/entity\/includes\/entity.inc":424,"sites\/all\/modules\/entity\/includes\/entity.controller.inc":982,"sites\/all\/modules\/entity\/includes\/entity.wrapper.inc":1274,"sites\/all\/modules\/entity\/includes\/entity.property.inc":658,"sites\/all\/modules\/entity\/includes\/entity.ui.inc":768},"lines":14307},{"name":"eu_cookie_compliance","version":"0","type":"Contrib","files":{"sites\/all\/modules\/eu_cookie_compliance\/eu_cookie_compliance.admin.inc":252,"sites\/all\/modules\/eu_cookie_compliance\/theme\/eu-cookie-compliance-popup-info.tpl.php":30,"sites\/all\/modules\/eu_cookie_compliance\/theme\/eu-cookie-compliance-popup-agreed.tpl.php":29,"sites\/all\/modules\/eu_cookie_compliance\/css\/eu_cookie_compliance.css":117,"sites\/all\/modules\/eu_cookie_compliance\/eu_cookie_compliance.module":186,"sites\/all\/modules\/eu_cookie_compliance\/js\/eu_cookie_compliance.js":193,"sites\/all\/modules\/eu_cookie_compliance\/eu_cookie_compliance.install":41},"lines":848},{"name":"field","version":"7004","type":"Core","files":[],"lines":0},{"name":"field_sql_storage","version":"7002","type":"Core","files":[],"lines":0},{"name":"field_ui","version":"0","type":"Core","files":[],"lines":0},{"name":"file","version":"0","type":"Core","files":[],"lines":0},{"name":"filter","version":"7010","type":"Core","files":[],"lines":0},{"name":"footnotes","version":"0","type":"Contrib","files":{"sites\/all\/modules\/footnotes\/footnotes.module":440,"sites\/all\/modules\/footnotes\/footnotes_views_handler_field_body_content.inc":34,"sites\/all\/modules\/footnotes\/footnotes_views_handler_field_body_footnotes.inc":31,"sites\/all\/modules\/footnotes\/footnotes-alternative_layout.css":88,"sites\/all\/modules\/footnotes\/footnotes_views_handler_field.inc":19,"sites\/all\/modules\/footnotes\/footnotes_wysiwyg\/footnotes_wysiwyg.module":43,"sites\/all\/modules\/footnotes\/footnotes_wysiwyg\/ckeditor_plugin\/plugin.js":183,"sites\/all\/modules\/footnotes\/footnotes_wysiwyg\/tinymce_plugin\/tiny_mce_popup.js":5,"sites\/all\/modules\/footnotes\/footnotes_wysiwyg\/tinymce_plugin\/langs\/en.js":4,"sites\/all\/modules\/footnotes\/footnotes_wysiwyg\/tinymce_plugin\/langs\/en_dlg.js":4,"sites\/all\/modules\/footnotes\/footnotes_wysiwyg\/tinymce_plugin\/editor_plugin.js":57,"sites\/all\/modules\/footnotes\/footnotes_wysiwyg\/tinymce_plugin\/footnote.htm":67,"sites\/all\/modules\/footnotes\/footnotes_wysiwyg\/tinymce_plugin\/footnote.js":19,"sites\/all\/modules\/footnotes\/footnotes_views.module":20,"sites\/all\/modules\/footnotes\/footnotes_views.views.inc":95,"sites\/all\/modules\/footnotes\/footnotes.css":94},"lines":1203},{"name":"help","version":"0","type":"Core","files":[],"lines":0},{"name":"image","version":"7005","type":"Core","files":[],"lines":0},{"name":"list","version":"7002","type":"Core","files":[],"lines":0},{"name":"locale","version":"7005","type":"Core","files":[],"lines":0},{"name":"menu","version":"7003","type":"Core","files":[],"lines":0},{"name":"node","version":"7016","type":"Core","files":[],"lines":0},{"name":"number","version":"0","type":"Core","files":[],"lines":0},{"name":"options","version":"0","type":"Core","files":[],"lines":0},{"name":"path","version":"0","type":"Core","files":[],"lines":0},{"name":"php","version":"0","type":"Core","files":[],"lines":0},{"name":"poll","version":"7004","type":"Core","files":[],"lines":0},{"name":"profile","version":"7002","type":"Core","files":[],"lines":0},{"name":"rdf","version":"0","type":"Core","files":[],"lines":0},{"name":"search","version":"7000","type":"Core","files":[],"lines":0},{"name":"shortcut","version":"0","type":"Core","files":[],"lines":0},{"name":"socialmedia","version":"7001","type":"Feature","files":{"sites\/all\/modules\/socialmedia\/socialmedia.admin.css":38,"sites\/all\/modules\/socialmedia\/socialmedia.setup.inc":417,"sites\/all\/modules\/socialmedia\/socialmedia.icons.inc":341,"sites\/all\/modules\/socialmedia\/socialmedia.platforms.inc":1106,"sites\/all\/modules\/socialmedia\/socialmedia.widgets.inc":1379,"sites\/all\/modules\/socialmedia\/socialmedia.features.inc":85,"sites\/all\/modules\/socialmedia\/socialmedia.admin.inc":629,"sites\/all\/modules\/socialmedia\/socialmedia.module":570,"sites\/all\/modules\/socialmedia\/socialmedia.app.inc":24,"sites\/all\/modules\/socialmedia\/socialmedia.tokens.inc":207,"sites\/all\/modules\/socialmedia\/socialmedia.install":114},"lines":4910},{"name":"system","version":"7081","type":"Core","files":[],"lines":0},{"name":"taxonomy","version":"7011","type":"Core","files":[],"lines":0},{"name":"term_merge","version":"0","type":"Contrib","files":{"sites\/all\/modules\/term_merge\/term_merge.api.php":29,"sites\/all\/modules\/term_merge\/term_merge.pages.inc":718,"sites\/all\/modules\/term_merge\/term_merge.batch.inc":103,"sites\/all\/modules\/term_merge\/term_merge.module":1078,"sites\/all\/modules\/term_merge\/term_merge.test":1723,"sites\/all\/modules\/term_merge\/plugins\/duplicate_suggestion\/description.inc":20,"sites\/all\/modules\/term_merge\/plugins\/duplicate_suggestion\/parent.inc":20,"sites\/all\/modules\/term_merge\/plugins\/duplicate_suggestion\/name.inc":29,"sites\/all\/modules\/term_merge\/plugins\/behavior\/term_merge.inc":13,"sites\/all\/modules\/term_merge\/help\/term_merge.help.ini":10,"sites\/all\/modules\/term_merge\/help\/term_merge_duplicate_suggestion.html":17,"sites\/all\/modules\/term_merge\/help\/term_merge.html":45,"sites\/all\/modules\/term_merge\/includes\/EntityReferenceTermMergeSynonymsBehavior.class.inc":51,"sites\/all\/modules\/term_merge\/includes\/TaxonomyTermReferenceTermMergeSynonymsBehavior.class.inc":73,"sites\/all\/modules\/term_merge\/includes\/TermMergeSynonymsBehavior.interface.inc":36,"sites\/all\/modules\/term_merge\/includes\/TextTermMergeSynonymsBehavior.class.inc":57,"sites\/all\/modules\/term_merge\/js\/duplicate.form.js":67},"lines":4089},{"name":"text","version":"7000","type":"Core","files":[],"lines":0},{"name":"toolbar","version":"0","type":"Core","files":[],"lines":0},{"name":"tracker","version":"7000","type":"Core","files":[],"lines":0},{"name":"translation","version":"0","type":"Core","files":[],"lines":0},{"name":"trigger","version":"7002","type":"Core","files":[],"lines":0},{"name":"twitter_block","version":"7201","type":"Contrib","files":{"sites\/all\/modules\/twitter_block\/tests\/twitter_block.test":109,"sites\/all\/modules\/twitter_block\/twitter_block.install":122,"sites\/all\/modules\/twitter_block\/twitter_block.admin.inc":195,"sites\/all\/modules\/twitter_block\/twitter_block.module":571},"lines":997},{"name":"update","version":"7001","type":"Core","files":[],"lines":0},{"name":"user","version":"7019","type":"Core","files":[],"lines":0},{"name":"widgets","version":"0","type":"Contrib","files":{"sites\/all\/modules\/widgets\/widgets.css":11,"sites\/all\/modules\/widgets\/widgets-rtl.css":12,"sites\/all\/modules\/widgets\/widgets.admin.css":8,"sites\/all\/modules\/widgets\/widgets.tokens.inc":54,"sites\/all\/modules\/widgets\/widgets.api.php":202,"sites\/all\/modules\/widgets\/modules\/widgets_service_links\/widgets_service_links.module":79,"sites\/all\/modules\/widgets\/widgets.admin.inc":1263,"sites\/all\/modules\/widgets\/widgets.install":191,"sites\/all\/modules\/widgets\/widgets.module":1514,"sites\/all\/modules\/widgets\/widgets.elements.inc":23},"lines":3357},{"name":"xmlsitemap_node","version":"6201","type":"Contrib","files":{"sites\/all\/modules\/xmlsitemap\/xmlsitemap_node\/xmlsitemap_node.install":45,"sites\/all\/modules\/xmlsitemap\/xmlsitemap_node\/xmlsitemap_node.module":347,"sites\/all\/modules\/xmlsitemap\/xmlsitemap_node\/xmlsitemap_node.test":149},"lines":541},{"name":"xmlsitemap_taxonomy","version":"7200","type":"Contrib","files":{"sites\/all\/modules\/xmlsitemap\/xmlsitemap_taxonomy\/xmlsitemap_taxonomy.module":279,"sites\/all\/modules\/xmlsitemap\/xmlsitemap_taxonomy\/xmlsitemap_taxonomy.test":50,"sites\/all\/modules\/xmlsitemap\/xmlsitemap_taxonomy\/xmlsitemap_taxonomy.install":67},"lines":396},{"name":"xmlsitemap","version":"7203","type":"Contrib","files":{"sites\/all\/modules\/xmlsitemap\/xmlsitemap_menu\/xmlsitemap_menu.module":304,"sites\/all\/modules\/xmlsitemap\/xmlsitemap_menu\/xmlsitemap_menu.install":48,"sites\/all\/modules\/xmlsitemap\/xmlsitemap_menu\/xmlsitemap_menu.test":51,"sites\/all\/modules\/xmlsitemap\/xmlsitemap.module":1596,"sites\/all\/modules\/xmlsitemap\/xsl\/jquery.tablesorter.js":853,"sites\/all\/modules\/xmlsitemap\/xsl\/xmlsitemap.xsl.js":46,"sites\/all\/modules\/xmlsitemap\/xsl\/xmlsitemap.xsl.css":46,"sites\/all\/modules\/xmlsitemap\/xsl\/xmlsitemap.xsl":138,"sites\/all\/modules\/xmlsitemap\/xsl\/jquery.tablesorter.min.js":2,"sites\/all\/modules\/xmlsitemap\/xmlsitemap.api.php":290,"sites\/all\/modules\/xmlsitemap\/xmlsitemap.pages.inc":160,"sites\/all\/modules\/xmlsitemap\/xmlsitemap_taxonomy\/xmlsitemap_taxonomy.module":279,"sites\/all\/modules\/xmlsitemap\/xmlsitemap_taxonomy\/xmlsitemap_taxonomy.test":50,"sites\/all\/modules\/xmlsitemap\/xmlsitemap_taxonomy\/xmlsitemap_taxonomy.install":67,"sites\/all\/modules\/xmlsitemap\/xmlsitemap_modal\/xmlsitemap_modal.module":82,"sites\/all\/modules\/xmlsitemap\/xmlsitemap.generate.inc":552,"sites\/all\/modules\/xmlsitemap\/xmlsitemap.drush.inc":172,"sites\/all\/modules\/xmlsitemap\/xmlsitemap.install":571,"sites\/all\/modules\/xmlsitemap\/xmlsitemap_node\/xmlsitemap_node.install":45,"sites\/all\/modules\/xmlsitemap\/xmlsitemap_node\/xmlsitemap_node.module":347,"sites\/all\/modules\/xmlsitemap\/xmlsitemap_node\/xmlsitemap_node.test":149,"sites\/all\/modules\/xmlsitemap\/xmlsitemap_i18n\/xmlsitemap_i18n.test":140,"sites\/all\/modules\/xmlsitemap\/xmlsitemap_i18n\/xmlsitemap_i18n.module":117,"sites\/all\/modules\/xmlsitemap\/xmlsitemap.test":784,"sites\/all\/modules\/xmlsitemap\/xmlsitemap_engines\/xmlsitemap_engines.api.php":35,"sites\/all\/modules\/xmlsitemap\/xmlsitemap_engines\/tests\/xmlsitemap_engines.test":106,"sites\/all\/modules\/xmlsitemap\/xmlsitemap_engines\/tests\/xmlsitemap_engines_test.module":43,"sites\/all\/modules\/xmlsitemap\/xmlsitemap_engines\/xmlsitemap_engines.admin.inc":66,"sites\/all\/modules\/xmlsitemap\/xmlsitemap_engines\/xmlsitemap_engines.module":246,"sites\/all\/modules\/xmlsitemap\/xmlsitemap_engines\/xmlsitemap_engines.install":46,"sites\/all\/modules\/xmlsitemap\/xmlsitemap_user\/xmlsitemap_user.module":164,"sites\/all\/modules\/xmlsitemap\/xmlsitemap_user\/xmlsitemap_user.test":51,"sites\/all\/modules\/xmlsitemap\/xmlsitemap_user\/xmlsitemap_user.install":44,"sites\/all\/modules\/xmlsitemap\/xmlsitemap_custom\/xmlsitemap_custom.admin.inc":199,"sites\/all\/modules\/xmlsitemap\/xmlsitemap_custom\/xmlsitemap_custom.module":64,"sites\/all\/modules\/xmlsitemap\/xmlsitemap_custom\/xmlsitemap_custom.test":108,"sites\/all\/modules\/xmlsitemap\/xmlsitemap_custom\/xmlsitemap_custom.install":15,"sites\/all\/modules\/xmlsitemap\/xmlsitemap.xmlsitemap.inc":312,"sites\/all\/modules\/xmlsitemap\/xmlsitemap.admin.inc":878,"sites\/all\/modules\/xmlsitemap\/xmlsitemap.js":23,"sites\/all\/modules\/xmlsitemap\/xmlsitemap.inc":90},"lines":9379},{"name":"xmlsitemap_engines","version":"6202","type":"Contrib","files":{"sites\/all\/modules\/xmlsitemap\/xmlsitemap_engines\/xmlsitemap_engines.api.php":35,"sites\/all\/modules\/xmlsitemap\/xmlsitemap_engines\/tests\/xmlsitemap_engines.test":106,"sites\/all\/modules\/xmlsitemap\/xmlsitemap_engines\/tests\/xmlsitemap_engines_test.module":43,"sites\/all\/modules\/xmlsitemap\/xmlsitemap_engines\/xmlsitemap_engines.admin.inc":66,"sites\/all\/modules\/xmlsitemap\/xmlsitemap_engines\/xmlsitemap_engines.module":246,"sites\/all\/modules\/xmlsitemap\/xmlsitemap_engines\/xmlsitemap_engines.install":46},"lines":542},{"name":"biblio","version":"7024","type":"Contrib","files":{"sites\/all\/modules\/biblio\/changelog.html":326,"sites\/all\/modules\/biblio\/tests\/test.bib":24,"sites\/all\/modules\/biblio\/tests\/test.xml":1,"sites\/all\/modules\/biblio\/tests\/biblio.test":193,"sites\/all\/modules\/biblio\/tests\/import.export.test":120,"sites\/all\/modules\/biblio\/tests\/keyword.test":150,"sites\/all\/modules\/biblio\/tests\/contributor.test":130,"sites\/all\/modules\/biblio\/tests\/test.ens":37,"sites\/all\/modules\/biblio\/modules\/CiteProc\/biblio_citeproc.install":344,"sites\/all\/modules\/biblio\/modules\/CiteProc\/biblio_citeproc.module":192,"sites\/all\/modules\/biblio\/modules\/CiteProc\/CSL.inc":1745,"sites\/all\/modules\/biblio\/modules\/CiteProc\/locale\/locales-mn-MN.xml":307,"sites\/all\/modules\/biblio\/modules\/CiteProc\/locale\/locales-de-AT.xml":305,"sites\/all\/modules\/biblio\/modules\/CiteProc\/locale\/locales-uk-UA.xml":307,"sites\/all\/modules\/biblio\/modules\/CiteProc\/locale\/locales-fi-FI.xml":305,"sites\/all\/modules\/biblio\/modules\/CiteProc\/locale\/locales-da-DK.xml":306,"sites\/all\/modules\/biblio\/modules\/CiteProc\/locale\/locales-pl-PL.xml":306,"sites\/all\/modules\/biblio\/modules\/CiteProc\/locale\/locales-zh-CN.xml":305,"sites\/all\/modules\/biblio\/modules\/CiteProc\/locale\/locales-zh-TW.xml":306,"sites\/all\/modules\/biblio\/modules\/CiteProc\/locale\/locales-sl-SI.xml":306,"sites\/all\/modules\/biblio\/modules\/CiteProc\/locale\/locales-ru-RU.xml":307,"sites\/all\/modules\/biblio\/modules\/CiteProc\/locale\/locales-pt-PT.xml":306,"sites\/all\/modules\/biblio\/modules\/CiteProc\/locale\/locales-el-GR.xml":306,"sites\/all\/modules\/biblio\/modules\/CiteProc\/locale\/locales-he-IL.xml":305,"sites\/all\/modules\/biblio\/modules\/CiteProc\/locale\/locales-nn-NO.xml":305,"sites\/all\/modules\/biblio\/modules\/CiteProc\/locale\/locales-nl-NL.xml":305,"sites\/all\/modules\/biblio\/modules\/CiteProc\/locale\/locales-pt-BR.xml":305,"sites\/all\/modules\/biblio\/modules\/CiteProc\/locale\/locales-ko-KR.xml":306,"sites\/all\/modules\/biblio\/modules\/CiteProc\/locale\/locales-th-TH.xml":305,"sites\/all\/modules\/biblio\/modules\/CiteProc\/locale\/locales-es-ES.xml":306,"sites\/all\/modules\/biblio\/modules\/CiteProc\/locale\/locales-de-DE.xml":305,"sites\/all\/modules\/biblio\/modules\/CiteProc\/locale\/locales-sk-SK.xml":305,"sites\/all\/modules\/biblio\/modules\/CiteProc\/locale\/locales-af-ZA.xml":306,"sites\/all\/modules\/biblio\/modules\/CiteProc\/locale\/locales-ro-RO.xml":306,"sites\/all\/modules\/biblio\/modules\/CiteProc\/locale\/locales-en-GB.xml":305,"sites\/all\/modules\/biblio\/modules\/CiteProc\/locale\/locales-de-CH.xml":305,"sites\/all\/modules\/biblio\/modules\/CiteProc\/locale\/locales-ar-AR.xml":307,"sites\/all\/modules\/biblio\/modules\/CiteProc\/locale\/locales-nb-NO.xml":305,"sites\/all\/modules\/biblio\/modules\/CiteProc\/locale\/locales-tr-TR.xml":306,"sites\/all\/modules\/biblio\/modules\/CiteProc\/locale\/locales-et-EE.xml":305,"sites\/all\/modules\/biblio\/modules\/CiteProc\/locale\/locales-it-IT.xml":306,"sites\/all\/modules\/biblio\/modules\/CiteProc\/locale\/locales-ja-JP.xml":306,"sites\/all\/modules\/biblio\/modules\/CiteProc\/locale\/locales-bg-BG.xml":306,"sites\/all\/modules\/biblio\/modules\/CiteProc\/locale\/locales-en-US.xml":305,"sites\/all\/modules\/biblio\/modules\/CiteProc\/locale\/locales-is-IS.xml":305,"sites\/all\/modules\/biblio\/modules\/CiteProc\/locale\/locales-ca-AD.xml":306,"sites\/all\/modules\/biblio\/modules\/CiteProc\/locale\/locales-sv-SE.xml":306,"sites\/all\/modules\/biblio\/modules\/CiteProc\/locale\/locales-fr-FR.xml":307,"sites\/all\/modules\/biblio\/modules\/CiteProc\/locale\/locales-eu.xml":305,"sites\/all\/modules\/biblio\/modules\/CiteProc\/locale\/locales-cs-CZ.xml":305,"sites\/all\/modules\/biblio\/modules\/CiteProc\/locale\/locales-hu-HU.xml":306,"sites\/all\/modules\/biblio\/modules\/CiteProc\/locale\/locales-km-KH.xml":305,"sites\/all\/modules\/biblio\/modules\/CiteProc\/locale\/locales-vi-VN.xml":306,"sites\/all\/modules\/biblio\/modules\/CiteProc\/locale\/locales-sr-RS.xml":306,"sites\/all\/modules\/biblio\/modules\/CiteProc\/locale\/locales-fa-IR.xml":304,"sites\/all\/modules\/biblio\/modules\/CiteProc\/style\/nature.csl":115,"sites\/all\/modules\/biblio\/modules\/CiteProc\/style\/apa.csl":444,"sites\/all\/modules\/biblio\/modules\/CiteProc\/style\/cse.csl":185,"sites\/all\/modules\/biblio\/modules\/CiteProc\/style\/harvard1.csl":186,"sites\/all\/modules\/biblio\/modules\/CiteProc\/style\/national-library-of-medicine-grant.csl":255,"sites\/all\/modules\/biblio\/modules\/CiteProc\/style\/apsa.csl":236,"sites\/all\/modules\/biblio\/modules\/CiteProc\/style\/ieee.csl":300,"sites\/all\/modules\/biblio\/modules\/CiteProc\/style\/mhra.csl":417,"sites\/all\/modules\/biblio\/modules\/CiteProc\/style\/chicago-author-date.csl":482,"sites\/all\/modules\/biblio\/modules\/CiteProc\/style\/chicago-note-bibliography.csl":1017,"sites\/all\/modules\/biblio\/modules\/CiteProc\/style\/american-medical-association.csl":238,"sites\/all\/modules\/biblio\/modules\/CiteProc\/style\/chicago-fullnote-bibliography.csl":1046,"sites\/all\/modules\/biblio\/modules\/CiteProc\/style\/asa.csl":227,"sites\/all\/modules\/biblio\/modules\/CiteProc\/style\/vancouver.csl":268,"sites\/all\/modules\/biblio\/modules\/CiteProc\/style\/mla.csl":397,"sites\/all\/modules\/biblio\/modules\/CiteProc\/schema\/csl-terms.rng":149,"sites\/all\/modules\/biblio\/modules\/CiteProc\/schema\/csl.rng":1752,"sites\/all\/modules\/biblio\/modules\/CiteProc\/schema\/csl-variables.rng":103,"sites\/all\/modules\/biblio\/modules\/CiteProc\/schema\/csl-categories.rng":52,"sites\/all\/modules\/biblio\/modules\/CiteProc\/schema\/csl-types.rng":45,"sites\/all\/modules\/biblio\/modules\/CiteProc\/biblio_citeproc.admin.inc":711,"sites\/all\/modules\/biblio\/modules\/endnote\/endnote8_export.inc":202,"sites\/all\/modules\/biblio\/modules\/endnote\/biblio_xml.module":140,"sites\/all\/modules\/biblio\/modules\/endnote\/endnote_xml_parser.inc":456,"sites\/all\/modules\/biblio\/modules\/endnote\/biblio_tagged.module":408,"sites\/all\/modules\/biblio\/modules\/endnote\/biblio_xml.install":391,"sites\/all\/modules\/biblio\/modules\/endnote\/biblio_tagged.install":197,"sites\/all\/modules\/biblio\/modules\/RIS\/biblio_ris.install":219,"sites\/all\/modules\/biblio\/modules\/RIS\/biblio_ris.module":491,"sites\/all\/modules\/biblio\/modules\/rtf\/rtf_export.inc":348,"sites\/all\/modules\/biblio\/modules\/rtf\/biblio_rtf.module":96,"sites\/all\/modules\/biblio\/modules\/rtf\/biblio_rtf.install":27,"sites\/all\/modules\/biblio\/modules\/marcParse\/php-marc.php":1016,"sites\/all\/modules\/biblio\/modules\/marcParse\/biblio_marc.install":97,"sites\/all\/modules\/biblio\/modules\/marcParse\/biblio_marc.module":377,"sites\/all\/modules\/biblio\/modules\/marcParse\/example.php":85,"sites\/all\/modules\/biblio\/modules\/marcParse\/example.mrc":1,"sites\/all\/modules\/biblio\/modules\/pubmed\/EntrezPubmedArticle.php":242,"sites\/all\/modules\/biblio\/modules\/pubmed\/biblio_pm.admin.inc":101,"sites\/all\/modules\/biblio\/modules\/pubmed\/biblio_pm.views.inc":158,"sites\/all\/modules\/biblio\/modules\/pubmed\/biblio_pm.module":525,"sites\/all\/modules\/biblio\/modules\/pubmed\/EntrezClient.php":506,"sites\/all\/modules\/biblio\/modules\/pubmed\/biblio_pm.install":158,"sites\/all\/modules\/biblio\/modules\/bibtexParse\/PARSEMONTH.php":118,"sites\/all\/modules\/biblio\/modules\/bibtexParse\/biblio_bibtex.install":166,"sites\/all\/modules\/biblio\/modules\/bibtexParse\/README":96,"sites\/all\/modules\/biblio\/modules\/bibtexParse\/PARSECREATORS.php":320,"sites\/all\/modules\/biblio\/modules\/bibtexParse\/biblio_bibtex.module":456,"sites\/all\/modules\/biblio\/modules\/bibtexParse\/CHANGELOG":84,"sites\/all\/modules\/biblio\/modules\/bibtexParse\/transtab_latex_unicode.inc.php":257,"sites\/all\/modules\/biblio\/modules\/bibtexParse\/LICENSE":251,"sites\/all\/modules\/biblio\/modules\/bibtexParse\/PARSEPAGE.php":67,"sites\/all\/modules\/biblio\/modules\/bibtexParse\/PARSEENTRIES.php":562,"sites\/all\/modules\/biblio\/modules\/bibtexParse\/transtab_unicode_bibtex.inc.php":849,"sites\/all\/modules\/biblio\/modules\/bibtexParse\/bib.bib":45,"sites\/all\/modules\/biblio\/modules\/crossref\/biblio.crossref.client.php":326,"sites\/all\/modules\/biblio\/modules\/crossref\/biblio_crossref.install":152,"sites\/all\/modules\/biblio\/modules\/crossref\/biblio_crossref.module":169,"sites\/all\/modules\/biblio\/views\/biblio_handler_field_biblio_keyword_kid.inc":41,"sites\/all\/modules\/biblio\/views\/biblio_handler_field_contributor.inc":279,"sites\/all\/modules\/biblio\/views\/biblio.views.inc":442,"sites\/all\/modules\/biblio\/views\/biblio_handler_field.inc":71,"sites\/all\/modules\/biblio\/views\/biblio_handler_field_biblio_type.inc":42,"sites\/all\/modules\/biblio\/views\/biblio_handler_filter_contributor_uid.inc":18,"sites\/all\/modules\/biblio\/views\/biblio_handler_citation.inc":128,"sites\/all\/modules\/biblio\/views\/biblio.views_default.inc":642,"sites\/all\/modules\/biblio\/views\/biblio_handler_field_biblio_keyword_data_word.inc":61,"sites\/all\/modules\/biblio\/views\/biblio_handler_argument_many_to_one.inc":22,"sites\/all\/modules\/biblio\/views\/biblio_handler_filter_biblio_keyword_kid.inc":118,"sites\/all\/modules\/biblio\/views\/biblio_handler_field_keyword.inc":61,"sites\/all\/modules\/biblio\/views\/biblio_handler_filter_contributor_lastname.inc":16,"sites\/all\/modules\/biblio\/views\/biblio_handler_filter_biblio_contributor_auth_type.inc":24,"sites\/all\/modules\/biblio\/views\/biblio_handler_filter_biblio_type.inc":24,"sites\/all\/modules\/biblio\/views\/biblio_handler_field_markup.inc":27,"sites\/all\/modules\/biblio\/views\/biblio_handler_filter_biblio_keyword_word.inc":73,"sites\/all\/modules\/biblio\/views\/biblio_handler_field_export_link.inc":44,"sites\/all\/modules\/biblio\/views\/biblio_handler_filter_contributor.inc":16,"sites\/all\/modules\/biblio\/views\/biblio_handler_sort_contributor_lastname.inc":40,"sites\/all\/modules\/biblio\/biblio.tokens.inc":90,"sites\/all\/modules\/biblio\/biblio.module":2259,"sites\/all\/modules\/biblio\/includes\/biblio_xml.inc":69,"sites\/all\/modules\/biblio\/includes\/biblio.admin.inc":2926,"sites\/all\/modules\/biblio\/includes\/biblio.search.inc":304,"sites\/all\/modules\/biblio\/includes\/biblio.import.export.inc":874,"sites\/all\/modules\/biblio\/includes\/biblio.util.inc":387,"sites\/all\/modules\/biblio\/includes\/Parser.php":215,"sites\/all\/modules\/biblio\/includes\/biblio.pages.inc":1343,"sites\/all\/modules\/biblio\/includes\/biblio_theme.inc":1255,"sites\/all\/modules\/biblio\/includes\/biblio.keywords.inc":486,"sites\/all\/modules\/biblio\/includes\/biblio.feeds.inc":211,"sites\/all\/modules\/biblio\/includes\/biblio.contributors.inc":626,"sites\/all\/modules\/biblio\/includes\/biblio.fields.inc":51,"sites\/all\/modules\/biblio\/includes\/Name.php":103,"sites\/all\/modules\/biblio\/styles\/biblio_style_classic.inc":86,"sites\/all\/modules\/biblio\/styles\/biblio_style_ama.inc":512,"sites\/all\/modules\/biblio\/styles\/biblio_style_chicago.inc":474,"sites\/all\/modules\/biblio\/styles\/biblio_style_cse.inc":91,"sites\/all\/modules\/biblio\/styles\/biblio_style_mla.inc":507,"sites\/all\/modules\/biblio\/styles\/biblio_style_ieee.inc":111,"sites\/all\/modules\/biblio\/styles\/biblio_style_apa.inc":107,"sites\/all\/modules\/biblio\/styles\/biblio_style_vancouver.inc":538,"sites\/all\/modules\/biblio\/misc\/biblio.nodeformbuttonhide.js":5,"sites\/all\/modules\/biblio\/misc\/biblio.field.type.data.csv":41,"sites\/all\/modules\/biblio\/misc\/biblio.field.link.data.csv":55,"sites\/all\/modules\/biblio\/misc\/biblio.highlight.js":9,"sites\/all\/modules\/biblio\/biblio.install":2219,"sites\/all\/modules\/biblio\/biblio.css":338},"lines":53975},{"name":"biblio_pm","version":"7004","type":"Contrib","files":{"sites\/all\/modules\/biblio\/modules\/pubmed\/EntrezPubmedArticle.php":242,"sites\/all\/modules\/biblio\/modules\/pubmed\/biblio_pm.admin.inc":101,"sites\/all\/modules\/biblio\/modules\/pubmed\/biblio_pm.views.inc":158,"sites\/all\/modules\/biblio\/modules\/pubmed\/biblio_pm.module":525,"sites\/all\/modules\/biblio\/modules\/pubmed\/EntrezClient.php":506,"sites\/all\/modules\/biblio\/modules\/pubmed\/biblio_pm.install":158},"lines":1690},{"name":"biblio_crossref","version":"0","type":"Contrib","files":{"sites\/all\/modules\/biblio\/modules\/crossref\/biblio.crossref.client.php":326,"sites\/all\/modules\/biblio\/modules\/crossref\/biblio_crossref.install":152,"sites\/all\/modules\/biblio\/modules\/crossref\/biblio_crossref.module":169},"lines":647},{"name":"biblio_bibtex","version":"7001","type":"Contrib","files":{"sites\/all\/modules\/biblio\/modules\/bibtexParse\/PARSEMONTH.php":118,"sites\/all\/modules\/biblio\/modules\/bibtexParse\/biblio_bibtex.install":166,"sites\/all\/modules\/biblio\/modules\/bibtexParse\/README":96,"sites\/all\/modules\/biblio\/modules\/bibtexParse\/PARSECREATORS.php":320,"sites\/all\/modules\/biblio\/modules\/bibtexParse\/biblio_bibtex.module":456,"sites\/all\/modules\/biblio\/modules\/bibtexParse\/CHANGELOG":84,"sites\/all\/modules\/biblio\/modules\/bibtexParse\/transtab_latex_unicode.inc.php":257,"sites\/all\/modules\/biblio\/modules\/bibtexParse\/LICENSE":251,"sites\/all\/modules\/biblio\/modules\/bibtexParse\/PARSEPAGE.php":67,"sites\/all\/modules\/biblio\/modules\/bibtexParse\/PARSEENTRIES.php":562,"sites\/all\/modules\/biblio\/modules\/bibtexParse\/transtab_unicode_bibtex.inc.php":849,"sites\/all\/modules\/biblio\/modules\/bibtexParse\/bib.bib":45},"lines":3271},{"name":"biblio_rtf","version":"0","type":"Contrib","files":{"sites\/all\/modules\/biblio\/modules\/rtf\/rtf_export.inc":348,"sites\/all\/modules\/biblio\/modules\/rtf\/biblio_rtf.module":96,"sites\/all\/modules\/biblio\/modules\/rtf\/biblio_rtf.install":27},"lines":471},{"name":"biblio_tagged","version":"0","type":"Contrib","files":{"sites\/all\/modules\/biblio\/modules\/endnote\/endnote8_export.inc":202,"sites\/all\/modules\/biblio\/modules\/endnote\/biblio_xml.module":140,"sites\/all\/modules\/biblio\/modules\/endnote\/endnote_xml_parser.inc":456,"sites\/all\/modules\/biblio\/modules\/endnote\/biblio_tagged.module":408,"sites\/all\/modules\/biblio\/modules\/endnote\/biblio_xml.install":391,"sites\/all\/modules\/biblio\/modules\/endnote\/biblio_tagged.install":197},"lines":1794},{"name":"biblio_marc","version":"0","type":"Contrib","files":{"sites\/all\/modules\/biblio\/modules\/marcParse\/php-marc.php":1016,"sites\/all\/modules\/biblio\/modules\/marcParse\/biblio_marc.install":97,"sites\/all\/modules\/biblio\/modules\/marcParse\/biblio_marc.module":377,"sites\/all\/modules\/biblio\/modules\/marcParse\/example.php":85,"sites\/all\/modules\/biblio\/modules\/marcParse\/example.mrc":1},"lines":1576},{"name":"biblio_xml","version":"0","type":"Contrib","files":{"sites\/all\/modules\/biblio\/modules\/endnote\/endnote8_export.inc":202,"sites\/all\/modules\/biblio\/modules\/endnote\/biblio_xml.module":140,"sites\/all\/modules\/biblio\/modules\/endnote\/endnote_xml_parser.inc":456,"sites\/all\/modules\/biblio\/modules\/endnote\/biblio_tagged.module":408,"sites\/all\/modules\/biblio\/modules\/endnote\/biblio_xml.install":391,"sites\/all\/modules\/biblio\/modules\/endnote\/biblio_tagged.install":197},"lines":1794},{"name":"biblio_ris","version":"0","type":"Contrib","files":{"sites\/all\/modules\/biblio\/modules\/RIS\/biblio_ris.install":219,"sites\/all\/modules\/biblio\/modules\/RIS\/biblio_ris.module":491},"lines":710},{"name":"dblog","version":"7003","type":"Core","files":[],"lines":0},{"name":"mollom","version":"7215","type":"Core","files":[],"lines":0},{"name":"overlay","version":"0","type":"Core","files":[],"lines":0},{"name":"statistics","version":"7000","type":"Core","files":[],"lines":0}],"themes":[{"name":"boron","lines":963,"files":{"sites\/all\/themes\/boron\/templates\/node.tpl.php":122,"sites\/all\/themes\/boron\/templates\/html.tpl.php":52,"sites\/all\/themes\/boron\/templates\/block.tpl.php":58,"sites\/all\/themes\/boron\/templates\/comment.tpl.php":100,"sites\/all\/themes\/boron\/templates\/comment-wrapper.tpl.php":54,"sites\/all\/themes\/boron\/templates\/aggregator-summary-items.tpl.php":26,"sites\/all\/themes\/boron\/templates\/aggregator-item.tpl.php":48,"sites\/all\/themes\/boron\/templates\/page.tpl.php":160,"sites\/all\/themes\/boron\/templates\/book-navigation.tpl.php":52,"sites\/all\/themes\/boron\/templates\/aggregator-feed-source.tpl.php":37,"sites\/all\/themes\/boron\/theme-settings.php":58,"sites\/all\/themes\/boron\/template.php":109,"sites\/all\/themes\/boron\/css\/layout.css":87},"type":"Enabled"},{"name":"garland","lines":2485,"files":{"themes\/garland\/node.tpl.php":35,"themes\/garland\/fix-ie-rtl.css":62,"themes\/garland\/comment.tpl.php":32,"themes\/garland\/style-rtl.css":345,"themes\/garland\/page.tpl.php":69,"themes\/garland\/theme-settings.php":31,"themes\/garland\/fix-ie.css":66,"themes\/garland\/template.php":157,"themes\/garland\/maintenance-page.tpl.php":88,"themes\/garland\/color\/color.inc":221,"themes\/garland\/color\/preview.css":61,"themes\/garland\/style.css":1256,"themes\/garland\/print.css":62},"type":"Enabled"},{"name":"parish_theme","lines":2030,"files":{"sites\/all\/themes\/parish_theme\/templates\/page.tpl.php":181,"sites\/all\/themes\/parish_theme\/favicon.ico":3,"sites\/all\/themes\/parish_theme\/template.php":68,"sites\/all\/themes\/parish_theme\/css\/colors.css":40,"sites\/all\/themes\/parish_theme\/css\/style.css":751,"sites\/all\/themes\/parish_theme\/js\/html5.js":5,"sites\/all\/themes\/parish_theme\/js\/slicknav\/jquery.slicknav.min.js":6,"sites\/all\/themes\/parish_theme\/js\/slicknav\/jquery.slicknav.js":488,"sites\/all\/themes\/parish_theme\/js\/slicknav\/slicknav.min.css":5,"sites\/all\/themes\/parish_theme\/js\/slicknav\/slicknav.css":148,"sites\/all\/themes\/parish_theme\/js\/mobile-navigation.js":22,"sites\/all\/themes\/parish_theme\/js\/menu-submit.js":33,"sites\/all\/themes\/parish_theme\/color\/preview.js":47,"sites\/all\/themes\/parish_theme\/color\/color.inc":90,"sites\/all\/themes\/parish_theme\/color\/preview.html":36,"sites\/all\/themes\/parish_theme\/color\/preview.css":107},"type":"Default"},{"name":"profolio","lines":1569,"files":{"sites\/all\/themes\/profolio\/node.tpl.php":53,"sites\/all\/themes\/profolio\/html.tpl.php":28,"sites\/all\/themes\/profolio\/block.tpl.php":20,"sites\/all\/themes\/profolio\/comment.tpl.php":54,"sites\/all\/themes\/profolio\/region.tpl.php":11,"sites\/all\/themes\/profolio\/images\/profolio2_03.jpg":3,"sites\/all\/themes\/profolio\/images\/profolio2_01.jpg":3,"sites\/all\/themes\/profolio\/images\/profolio2_02.jpg":3,"sites\/all\/themes\/profolio\/images\/hoverstate.jpg":16,"sites\/all\/themes\/profolio\/images\/_notes\/dwsync.xml":13,"sites\/all\/themes\/profolio\/images\/menusplit_03.jpg":3,"sites\/all\/themes\/profolio\/images\/profolio2_05.jpg":3,"sites\/all\/themes\/profolio\/images\/logo_04.jpg":19,"sites\/all\/themes\/profolio\/comment-wrapper.tpl.php":26,"sites\/all\/themes\/profolio\/page.tpl.php":117,"sites\/all\/themes\/profolio\/region--footer_message.tpl.php":9,"sites\/all\/themes\/profolio\/overlay.tpl.php":22,"sites\/all\/themes\/profolio\/template.php":77,"sites\/all\/themes\/profolio\/css\/local.css":2,"sites\/all\/themes\/profolio\/css\/_notes\/dwsync.xml":7,"sites\/all\/themes\/profolio\/css\/ie_styles.css":7,"sites\/all\/themes\/profolio\/css\/style.css":934,"sites\/all\/themes\/profolio\/css\/print.css":4,"sites\/all\/themes\/profolio\/maintenance-page.tpl.php":135},"type":"Enabled"}]}}